{
    "subterm_length_freqs": {
        "1": 3745,
        "2": 17379,
        "3": 80626,
        "4": 343911,
        "5": 932653,
        "6": 1461454,
        "7": 1607500,
        "8": 1481961,
        "9": 1238761,
        "10": 970490,
        "11": 725769,
        "12": 526079,
        "13": 374348,
        "14": 265192,
        "15": 189763,
        "16": 139336,
        "17": 106330,
        "18": 84748,
        "19": 70409,
        "20": 60621,
        "21": 53724,
        "22": 48652,
        "23": 44804,
        "24": 41754,
        "25": 39220,
        "26": 37067,
        "27": 35207,
        "28": 33572,
        "29": 32102,
        "30": 30790,
        "31": 29598,
        "32": 28506,
        "33": 27503,
        "34": 26574,
        "35": 25719,
        "36": 24926,
        "37": 24187,
        "38": 23495,
        "39": 22843,
        "40": 22230,
        "41": 21647,
        "42": 21095,
        "43": 20565,
        "44": 20056,
        "45": 19571,
        "46": 19108,
        "47": 18668,
        "48": 18250,
        "49": 17846,
        "50": 17460,
        "51": 17083,
        "52": 16720,
        "53": 16370,
        "54": 16042,
        "55": 15725,
        "56": 15419,
        "57": 15120,
        "58": 14830,
        "59": 14545,
        "60": 14271,
        "61": 14005,
        "62": 13744,
        "63": 13485,
        "64": 13234,
        "65": 12987,
        "66": 12748,
        "67": 12515,
        "68": 12291,
        "69": 12077,
        "70": 11866,
        "71": 11660,
        "72": 11458,
        "73": 11262,
        "74": 11071,
        "75": 10882,
        "76": 10697,
        "77": 10514,
        "78": 10339,
        "79": 10170,
        "80": 10004,
        "81": 9839,
        "82": 9679,
        "83": 9523,
        "84": 9374,
        "85": 9227,
        "86": 9083,
        "87": 8941,
        "88": 8806,
        "89": 8672,
        "90": 8540,
        "91": 8408,
        "92": 8277,
        "93": 8147,
        "94": 8018,
        "95": 7894,
        "96": 7773,
        "97": 7654,
        "98": 7535,
        "99": 7419,
        "100": 7305,
        "101": 7193,
        "102": 7083,
        "103": 6973,
        "104": 6863,
        "105": 6754,
        "106": 6647,
        "107": 6544,
        "108": 6445,
        "109": 6348,
        "110": 6253,
        "111": 6160,
        "112": 6070,
        "113": 5981,
        "114": 5895,
        "115": 5812,
        "116": 5729,
        "117": 5648,
        "118": 5569,
        "119": 5492,
        "120": 5416,
        "121": 5341,
        "122": 5267,
        "123": 5193,
        "124": 5122,
        "125": 5054,
        "126": 4987,
        "127": 4920,
        "128": 4853,
        "129": 4787,
        "130": 4721,
        "131": 4656,
        "132": 4592,
        "133": 4528,
        "134": 4464,
        "135": 4401,
        "136": 4339,
        "137": 4277,
        "138": 4219,
        "139": 4161,
        "140": 4104,
        "141": 4047,
        "142": 3991,
        "143": 3935,
        "144": 3880,
        "145": 3827,
        "146": 3774,
        "147": 3721,
        "148": 3670,
        "149": 3619,
        "150": 3570,
        "151": 3521,
        "152": 3473,
        "153": 3426,
        "154": 3379,
        "155": 3333,
        "156": 3288,
        "157": 3243,
        "158": 3198,
        "159": 3154,
        "160": 3110,
        "161": 3066,
        "162": 3023,
        "163": 2981,
        "164": 2939,
        "165": 2897,
        "166": 2855,
        "167": 2815,
        "168": 2775,
        "169": 2735,
        "170": 2697,
        "171": 2660,
        "172": 2623,
        "173": 2587,
        "174": 2553,
        "175": 2520,
        "176": 2489,
        "177": 2460,
        "178": 2431,
        "179": 2404,
        "180": 2377,
        "181": 2351,
        "182": 2325,
        "183": 2300,
        "184": 2275,
        "185": 2250,
        "186": 2225,
        "187": 2200,
        "188": 2175,
        "189": 2150,
        "190": 2125,
        "191": 2100,
        "192": 2076,
        "193": 2052,
        "194": 2028,
        "195": 2004,
        "196": 1982,
        "197": 1961,
        "198": 1941,
        "199": 1922,
        "200": 1905,
        "201": 1889,
        "202": 1874,
        "203": 1859,
        "204": 1844,
        "205": 1829,
        "206": 1814,
        "207": 1799,
        "208": 1784,
        "209": 1770,
        "210": 1757,
        "211": 1744,
        "212": 1732,
        "213": 1720,
        "214": 1709,
        "215": 1698,
        "216": 1687,
        "217": 1676,
        "218": 1665,
        "219": 1655,
        "220": 1645,
        "221": 1636,
        "222": 1627,
        "223": 1618,
        "224": 1609,
        "225": 1600,
        "226": 1591,
        "227": 1582,
        "228": 1573,
        "229": 1564,
        "230": 1555,
        "231": 1546,
        "232": 1537,
        "233": 1528,
        "234": 1519,
        "235": 1510,
        "236": 1501,
        "237": 1492,
        "238": 1483,
        "239": 1474,
        "240": 1465,
        "241": 1456,
        "242": 1447,
        "243": 1438,
        "244": 1430,
        "245": 1422,
        "246": 1414,
        "247": 1406,
        "248": 1398,
        "249": 1390,
        "250": 1382,
        "251": 1374,
        "252": 1366,
        "253": 1358,
        "254": 1350,
        "255": 1342,
        "256": 1334,
        "257": 1326,
        "258": 1319,
        "259": 1312,
        "260": 1305,
        "261": 1298,
        "262": 1291,
        "263": 1284,
        "264": 1277,
        "265": 1270,
        "266": 1263,
        "267": 1256,
        "268": 1249,
        "269": 1242,
        "270": 1235,
        "271": 1228,
        "272": 1221,
        "273": 1214,
        "274": 1207,
        "275": 1200,
        "276": 1193,
        "277": 1186,
        "278": 1179,
        "279": 1172,
        "280": 1165,
        "281": 1158,
        "282": 1151,
        "283": 1144,
        "284": 1137,
        "285": 1130,
        "286": 1123,
        "287": 1116,
        "288": 1109,
        "289": 1102,
        "290": 1095,
        "291": 1089,
        "292": 1083,
        "293": 1077,
        "294": 1071,
        "295": 1065,
        "296": 1059,
        "297": 1053,
        "298": 1047,
        "299": 1041,
        "300": 1035,
        "301": 1029,
        "302": 1023,
        "303": 1017,
        "304": 1011,
        "305": 1005,
        "306": 999,
        "307": 993,
        "308": 987,
        "309": 981,
        "310": 975,
        "311": 969,
        "312": 963,
        "313": 957,
        "314": 951,
        "315": 945,
        "316": 939,
        "317": 933,
        "318": 927,
        "319": 921,
        "320": 915,
        "321": 909,
        "322": 903,
        "323": 897,
        "324": 891,
        "325": 885,
        "326": 879,
        "327": 873,
        "328": 867,
        "329": 861,
        "330": 855,
        "331": 849,
        "332": 843,
        "333": 837,
        "334": 831,
        "335": 825,
        "336": 819,
        "337": 813,
        "338": 807,
        "339": 801,
        "340": 795,
        "341": 789,
        "342": 783,
        "343": 777,
        "344": 771,
        "345": 765,
        "346": 759,
        "347": 753,
        "348": 747,
        "349": 741,
        "350": 735,
        "351": 729,
        "352": 723,
        "353": 717,
        "354": 711,
        "355": 705,
        "356": 699,
        "357": 693,
        "358": 687,
        "359": 681,
        "360": 675,
        "361": 670,
        "362": 665,
        "363": 660,
        "364": 655,
        "365": 650,
        "366": 645,
        "367": 640,
        "368": 635,
        "369": 630,
        "370": 625,
        "371": 621,
        "372": 617,
        "373": 613,
        "374": 609,
        "375": 605,
        "376": 601,
        "377": 597,
        "378": 593,
        "379": 589,
        "380": 585,
        "381": 581,
        "382": 577,
        "383": 573,
        "384": 569,
        "385": 565,
        "386": 561,
        "387": 557,
        "388": 553,
        "389": 549,
        "390": 545,
        "391": 541,
        "392": 537,
        "393": 533,
        "394": 529,
        "395": 525,
        "396": 521,
        "397": 517,
        "398": 513,
        "399": 509,
        "400": 505,
        "401": 501,
        "402": 497,
        "403": 493,
        "404": 489,
        "405": 485,
        "406": 481,
        "407": 477,
        "408": 473,
        "409": 469,
        "410": 465,
        "411": 461,
        "412": 457,
        "413": 453,
        "414": 449,
        "415": 446,
        "416": 443,
        "417": 440,
        "418": 437,
        "419": 434,
        "420": 431,
        "421": 428,
        "422": 425,
        "423": 422,
        "424": 419,
        "425": 416,
        "426": 413,
        "427": 410,
        "428": 407,
        "429": 404,
        "430": 401,
        "431": 398,
        "432": 395,
        "433": 392,
        "434": 389,
        "435": 386,
        "436": 383,
        "437": 380,
        "438": 377,
        "439": 374,
        "440": 372,
        "441": 370,
        "442": 368,
        "443": 366,
        "444": 364,
        "445": 362,
        "446": 360,
        "447": 358,
        "448": 356,
        "449": 354,
        "450": 352,
        "451": 350,
        "452": 348,
        "453": 346,
        "454": 344,
        "455": 342,
        "456": 340,
        "457": 338,
        "458": 336,
        "459": 334,
        "460": 332,
        "461": 330,
        "462": 328,
        "463": 326,
        "464": 324,
        "465": 322,
        "466": 320,
        "467": 318,
        "468": 316,
        "469": 315,
        "470": 314,
        "471": 313,
        "472": 312,
        "473": 311,
        "474": 310,
        "475": 309,
        "476": 308,
        "477": 307,
        "478": 306,
        "479": 305,
        "480": 304,
        "481": 303,
        "482": 302,
        "483": 301,
        "484": 300,
        "485": 299,
        "486": 298,
        "487": 297,
        "488": 296,
        "489": 295,
        "490": 294,
        "491": 293,
        "492": 292,
        "493": 291,
        "494": 290,
        "495": 289,
        "496": 288,
        "497": 287,
        "498": 286,
        "499": 285,
        "500": 284,
        "501": 283,
        "502": 282,
        "503": 281,
        "504": 280,
        "505": 279,
        "506": 278,
        "507": 277,
        "508": 276,
        "509": 275,
        "510": 274,
        "511": 273,
        "512": 272,
        "513": 271,
        "514": 270,
        "515": 269,
        "516": 268,
        "517": 267,
        "518": 266,
        "519": 265,
        "520": 264,
        "521": 263,
        "522": 262,
        "523": 261,
        "524": 260,
        "525": 259,
        "526": 258,
        "527": 257,
        "528": 256,
        "529": 255,
        "530": 254,
        "531": 253,
        "532": 252,
        "533": 251,
        "534": 250,
        "535": 249,
        "536": 248,
        "537": 247,
        "538": 246,
        "539": 245,
        "540": 244,
        "541": 243,
        "542": 242,
        "543": 241,
        "544": 240,
        "545": 239,
        "546": 238,
        "547": 237,
        "548": 236,
        "549": 235,
        "550": 234,
        "551": 233,
        "552": 232,
        "553": 231,
        "554": 230,
        "555": 229,
        "556": 228,
        "557": 227,
        "558": 226,
        "559": 225,
        "560": 224,
        "561": 223,
        "562": 222,
        "563": 221,
        "564": 220,
        "565": 219,
        "566": 218,
        "567": 217,
        "568": 216,
        "569": 215,
        "570": 214,
        "571": 213,
        "572": 212,
        "573": 211,
        "574": 210,
        "575": 209,
        "576": 208,
        "577": 207,
        "578": 206,
        "579": 205,
        "580": 204,
        "581": 203,
        "582": 202,
        "583": 201,
        "584": 200,
        "585": 199,
        "586": 198,
        "587": 197,
        "588": 196,
        "589": 195,
        "590": 194,
        "591": 193,
        "592": 192,
        "593": 191,
        "594": 190,
        "595": 189,
        "596": 188,
        "597": 187,
        "598": 186,
        "599": 185,
        "600": 184,
        "601": 183,
        "602": 182,
        "603": 181,
        "604": 180,
        "605": 179,
        "606": 178,
        "607": 177,
        "608": 176,
        "609": 175,
        "610": 174,
        "611": 173,
        "612": 172,
        "613": 171,
        "614": 170,
        "615": 169,
        "616": 168,
        "617": 167,
        "618": 166,
        "619": 165,
        "620": 164,
        "621": 163,
        "622": 162,
        "623": 161,
        "624": 160,
        "625": 159,
        "626": 158,
        "627": 157,
        "628": 156,
        "629": 155,
        "630": 154,
        "631": 153,
        "632": 152,
        "633": 151,
        "634": 150,
        "635": 149,
        "636": 148,
        "637": 147,
        "638": 146,
        "639": 145,
        "640": 144,
        "641": 143,
        "642": 142,
        "643": 141,
        "644": 140,
        "645": 139,
        "646": 138,
        "647": 137,
        "648": 136,
        "649": 135,
        "650": 134,
        "651": 133,
        "652": 132,
        "653": 131,
        "654": 130,
        "655": 129,
        "656": 128,
        "657": 127,
        "658": 126,
        "659": 125,
        "660": 124,
        "661": 123,
        "662": 122,
        "663": 121,
        "664": 120,
        "665": 119,
        "666": 118,
        "667": 117,
        "668": 116,
        "669": 115,
        "670": 114,
        "671": 113,
        "672": 112,
        "673": 111,
        "674": 110,
        "675": 109,
        "676": 108,
        "677": 107,
        "678": 106,
        "679": 105,
        "680": 104,
        "681": 103,
        "682": 102,
        "683": 101,
        "684": 100,
        "685": 99,
        "686": 98,
        "687": 97,
        "688": 96,
        "689": 95,
        "690": 94,
        "691": 93,
        "692": 92,
        "693": 91,
        "694": 90,
        "695": 89,
        "696": 88,
        "697": 87,
        "698": 86,
        "699": 85,
        "700": 84,
        "701": 83,
        "702": 82,
        "703": 81,
        "704": 80,
        "705": 79,
        "706": 78,
        "707": 77,
        "708": 76,
        "709": 75,
        "710": 74,
        "711": 73,
        "712": 72,
        "713": 71,
        "714": 70,
        "715": 69,
        "716": 68,
        "717": 67,
        "718": 66,
        "719": 65,
        "720": 64,
        "721": 63,
        "722": 62,
        "723": 61,
        "724": 60,
        "725": 59,
        "726": 58,
        "727": 57,
        "728": 56,
        "729": 55,
        "730": 54,
        "731": 53,
        "732": 52,
        "733": 51,
        "734": 50,
        "735": 49,
        "736": 48,
        "737": 47,
        "738": 46,
        "739": 45,
        "740": 44,
        "741": 43,
        "742": 42,
        "743": 41,
        "744": 40,
        "745": 39,
        "746": 38,
        "747": 37,
        "748": 36,
        "749": 35,
        "750": 34,
        "751": 33,
        "752": 32,
        "753": 31,
        "754": 30,
        "755": 29,
        "756": 28,
        "757": 27,
        "758": 26,
        "759": 25,
        "760": 24,
        "761": 23,
        "762": 22,
        "763": 21,
        "764": 20,
        "765": 19,
        "766": 18,
        "767": 17,
        "768": 16,
        "769": 15,
        "770": 14,
        "771": 13,
        "772": 12,
        "773": 11,
        "774": 10,
        "775": 9,
        "776": 8,
        "777": 7,
        "778": 6,
        "779": 5,
        "780": 4,
        "781": 3,
        "782": 2,
        "783": 1
    }
}
