{
    "subterm_length_freqs": {
        "1": 312,
        "2": 2647,
        "3": 9138,
        "4": 15190,
        "5": 15963,
        "6": 13444,
        "7": 10222,
        "8": 7225,
        "9": 4862,
        "10": 3170,
        "11": 2056,
        "12": 1362,
        "13": 922,
        "14": 663,
        "15": 497,
        "16": 381,
        "17": 301,
        "18": 244,
        "19": 205,
        "20": 175,
        "21": 150,
        "22": 130,
        "23": 115,
        "24": 103,
        "25": 96,
        "26": 89,
        "27": 84,
        "28": 79,
        "29": 74,
        "30": 70,
        "31": 66,
        "32": 62,
        "33": 58,
        "34": 54,
        "35": 51,
        "36": 49,
        "37": 47,
        "38": 45,
        "39": 43,
        "40": 41,
        "41": 39,
        "42": 37,
        "43": 35,
        "44": 34,
        "45": 33,
        "46": 32,
        "47": 31,
        "48": 30,
        "49": 29,
        "50": 28,
        "51": 27,
        "52": 26,
        "53": 25,
        "54": 24,
        "55": 23,
        "56": 22,
        "57": 21,
        "58": 20,
        "59": 19,
        "60": 18,
        "61": 17,
        "62": 16,
        "63": 15,
        "64": 14,
        "65": 13,
        "66": 12,
        "67": 11,
        "68": 10,
        "69": 9,
        "70": 8,
        "71": 7,
        "72": 6,
        "73": 5,
        "74": 4,
        "75": 3,
        "76": 2,
        "77": 1
    }
}
