{
    "subterm_length_freqs": {
        "1": 305,
        "2": 4864,
        "3": 17122,
        "4": 26837,
        "5": 28289,
        "6": 23792,
        "7": 18403,
        "8": 13627,
        "9": 9842,
        "10": 6984,
        "11": 4950,
        "12": 3549,
        "13": 2634,
        "14": 2020,
        "15": 1604,
        "16": 1312,
        "17": 1084,
        "18": 901,
        "19": 747,
        "20": 628,
        "21": 525,
        "22": 439,
        "23": 366,
        "24": 305,
        "25": 254,
        "26": 214,
        "27": 180,
        "28": 151,
        "29": 123,
        "30": 102,
        "31": 84,
        "32": 69,
        "33": 56,
        "34": 45,
        "35": 37,
        "36": 30,
        "37": 24,
        "38": 19,
        "39": 15,
        "40": 11,
        "41": 7,
        "42": 4,
        "43": 2,
        "44": 1
    }
}
