{
    "subterm_length_freqs": {
        "1": 620,
        "2": 3015,
        "3": 13688,
        "4": 40086,
        "5": 61228,
        "6": 60899,
        "7": 50382,
        "8": 37982,
        "9": 26813,
        "10": 18374,
        "11": 12478,
        "12": 8620,
        "13": 6086,
        "14": 4452,
        "15": 3349,
        "16": 2622,
        "17": 2084,
        "18": 1692,
        "19": 1419,
        "20": 1208,
        "21": 1036,
        "22": 894,
        "23": 774,
        "24": 671,
        "25": 590,
        "26": 525,
        "27": 471,
        "28": 425,
        "29": 386,
        "30": 352,
        "31": 322,
        "32": 296,
        "33": 275,
        "34": 257,
        "35": 240,
        "36": 227,
        "37": 215,
        "38": 203,
        "39": 192,
        "40": 182,
        "41": 174,
        "42": 169,
        "43": 165,
        "44": 161,
        "45": 158,
        "46": 155,
        "47": 152,
        "48": 149,
        "49": 146,
        "50": 143,
        "51": 140,
        "52": 137,
        "53": 134,
        "54": 131,
        "55": 128,
        "56": 125,
        "57": 122,
        "58": 119,
        "59": 116,
        "60": 113,
        "61": 110,
        "62": 107,
        "63": 104,
        "64": 101,
        "65": 98,
        "66": 95,
        "67": 93,
        "68": 91,
        "69": 89,
        "70": 87,
        "71": 85,
        "72": 83,
        "73": 81,
        "74": 79,
        "75": 77,
        "76": 75,
        "77": 73,
        "78": 71,
        "79": 70,
        "80": 69,
        "81": 68,
        "82": 67,
        "83": 66,
        "84": 65,
        "85": 64,
        "86": 63,
        "87": 62,
        "88": 61,
        "89": 60,
        "90": 59,
        "91": 58,
        "92": 57,
        "93": 56,
        "94": 55,
        "95": 54,
        "96": 53,
        "97": 52,
        "98": 51,
        "99": 50,
        "100": 49,
        "101": 48,
        "102": 47,
        "103": 46,
        "104": 45,
        "105": 44,
        "106": 43,
        "107": 42,
        "108": 41,
        "109": 40,
        "110": 39,
        "111": 38,
        "112": 37,
        "113": 36,
        "114": 35,
        "115": 34,
        "116": 33,
        "117": 32,
        "118": 31,
        "119": 30,
        "120": 29,
        "121": 28,
        "122": 27,
        "123": 26,
        "124": 25,
        "125": 24,
        "126": 23,
        "127": 22,
        "128": 21,
        "129": 20,
        "130": 19,
        "131": 18,
        "132": 17,
        "133": 16,
        "134": 15,
        "135": 14,
        "136": 13,
        "137": 12,
        "138": 11,
        "139": 10,
        "140": 9,
        "141": 8,
        "142": 7,
        "143": 6,
        "144": 5,
        "145": 4,
        "146": 3,
        "147": 2,
        "148": 1
    }
}
