{
    "subterm_length_freqs": {
        "1": 552,
        "2": 3065,
        "3": 15441,
        "4": 43931,
        "5": 68245,
        "6": 72767,
        "7": 64873,
        "8": 52597,
        "9": 39738,
        "10": 28278,
        "11": 19166,
        "12": 12532,
        "13": 8054,
        "14": 5149,
        "15": 3332,
        "16": 2211,
        "17": 1508,
        "18": 1064,
        "19": 795,
        "20": 614,
        "21": 492,
        "22": 402,
        "23": 337,
        "24": 290,
        "25": 253,
        "26": 225,
        "27": 199,
        "28": 176,
        "29": 161,
        "30": 148,
        "31": 135,
        "32": 125,
        "33": 116,
        "34": 108,
        "35": 101,
        "36": 95,
        "37": 90,
        "38": 85,
        "39": 80,
        "40": 75,
        "41": 70,
        "42": 65,
        "43": 60,
        "44": 56,
        "45": 52,
        "46": 48,
        "47": 44,
        "48": 40,
        "49": 37,
        "50": 34,
        "51": 31,
        "52": 28,
        "53": 26,
        "54": 24,
        "55": 23,
        "56": 22,
        "57": 21,
        "58": 20,
        "59": 19,
        "60": 18,
        "61": 17,
        "62": 16,
        "63": 15,
        "64": 14,
        "65": 13,
        "66": 12,
        "67": 11,
        "68": 10,
        "69": 9,
        "70": 8,
        "71": 7,
        "72": 6,
        "73": 5,
        "74": 4,
        "75": 3,
        "76": 2,
        "77": 1
    }
}
